{"textures":{"0":"modelengine:entity/mob_ent_sage1","1":"modelengine:entity/mob_ent_sage","particle":"#0"},"elements":[{"from":[5.8700695,1.8488498,6.532445],"to":[5.8700695,2.8488498,10.032445],"faces":{"east":{"uv":[12.75,0.75,11.875,1.0],"tintindex":0,"rotation":0,"texture":"#0"},"west":{"uv":[11.875,0.75,12.75,1.0],"tintindex":0,"rotation":0,"texture":"#0"}},"rotation":{"origin":[5.8700695,2.3488498,8.282445],"angle":22.5,"axis":"x"}},{"from":[8.41671,4.42743,6.207415],"to":[8.41671,5.42743,9.207415],"faces":{"east":{"uv":[11.875,0.75,12.75,1.0],"tintindex":0,"rotation":0,"texture":"#0"},"west":{"uv":[12.75,0.75,11.875,1.0],"tintindex":0,"rotation":0,"texture":"#0"}},"rotation":{"origin":[7.7800503,5.1233597,8.985664],"angle":-22.5,"axis":"x"}},{"from":[6.1433897,-2.8730202,-1.5736895],"to":[8.14339,-1.3730202,1.4263101],"faces":{"east":{"uv":[7.125,5.0,6.375,5.375],"tintindex":0,"rotation":0,"texture":"#1"},"south":{"uv":[1.875,7.125,2.375,7.5],"tintindex":0,"rotation":0,"texture":"#1"},"north":{"uv":[7.125,1.75,7.625,2.125],"tintindex":0,"rotation":0,"texture":"#1"},"west":{"uv":[6.375,5.0,7.125,5.375],"tintindex":0,"rotation":0,"texture":"#1"},"up":{"uv":[6.25,5.75,5.75,5.0],"tintindex":0,"rotation":0,"texture":"#1"},"down":{"uv":[6.375,1.0,5.875,1.75],"tintindex":0,"rotation":0,"texture":"#1"}},"rotation":{"origin":[7.1433897,-3.8881855,-1.7138548],"angle":22.5,"axis":"x"}},{"from":[8.41671,6.42743,6.207415],"to":[8.41671,7.42743,9.207415],"faces":{"east":{"uv":[11.875,0.75,12.75,1.0],"tintindex":0,"rotation":0,"texture":"#0"},"west":{"uv":[12.75,0.75,11.875,1.0],"tintindex":0,"rotation":0,"texture":"#0"}},"rotation":{"origin":[7.7800503,7.1233597,8.985664],"angle":-22.5,"axis":"x"}},{"from":[5.8700695,-0.15114975,6.532445],"to":[5.8700695,0.8488498,10.032445],"faces":{"east":{"uv":[12.75,0.75,11.875,1.0],"tintindex":0,"rotation":0,"texture":"#0"},"west":{"uv":[11.875,0.75,12.75,1.0],"tintindex":0,"rotation":0,"texture":"#0"}},"rotation":{"origin":[5.8700695,0.34884977,8.282445],"angle":22.5,"axis":"x"}},{"from":[6.1433897,-1.5021248,6.782445],"to":[8.14339,3.9978752,9.782445],"faces":{"east":{"uv":[6.25,7.5,7.0,8.875],"tintindex":0,"rotation":0,"texture":"#0"},"south":{"uv":[0.375,9.0,0.875,10.375],"tintindex":0,"rotation":0,"texture":"#0"},"north":{"uv":[0.375,9.0,0.875,10.375],"tintindex":0,"rotation":0,"texture":"#0"},"west":{"uv":[6.25,7.5,7.0,8.875],"tintindex":0,"rotation":0,"texture":"#0"},"up":{"uv":[8.25,11.25,7.75,10.5],"tintindex":0,"rotation":0,"texture":"#0"},"down":{"uv":[2.125,10.75,1.625,11.5],"tintindex":0,"rotation":0,"texture":"#0"}}},{"from":[5.6433897,0.99787474,6.532445],"to":[8.64339,1.9978747,6.532445],"faces":{"south":{"uv":[12.25,12.0,11.5,12.25],"tintindex":0,"rotation":0,"texture":"#0"},"north":{"uv":[11.5,12.0,12.25,12.25],"tintindex":0,"rotation":0,"texture":"#0"}},"rotation":{"origin":[7.1433897,1.4978747,6.532445],"angle":22.5,"axis":"z"}},{"from":[6.0692654,8.26899,4.51084],"to":[7.569265,10.26899,5.51084],"faces":{"east":{"uv":[7.75,4.75,8.25,4.5],"tintindex":0,"rotation":270,"texture":"#1"},"south":{"uv":[7.25,4.625,7.625,5.125],"tintindex":0,"rotation":0,"texture":"#1"},"north":{"uv":[7.25,4.5,7.625,4.0],"tintindex":0,"rotation":180,"texture":"#1"},"west":{"uv":[4.25,8.0,4.75,7.75],"tintindex":0,"rotation":90,"texture":"#1"},"up":{"uv":[3.0,8.125,2.625,8.375],"tintindex":0,"rotation":0,"texture":"#1"},"down":{"uv":[8.5,1.75,8.125,2.0],"tintindex":0,"rotation":180,"texture":"#1"}},"rotation":{"origin":[5.820095,9.01899,5.974875],"angle":22.5,"axis":"y"}},{"from":[5.6433897,4.997875,6.532445],"to":[8.64339,5.997875,6.532445],"faces":{"south":{"uv":[12.25,12.0,11.5,12.25],"tintindex":0,"rotation":0,"texture":"#0"},"north":{"uv":[11.5,12.0,12.25,12.25],"tintindex":0,"rotation":0,"texture":"#0"}},"rotation":{"origin":[7.1433897,5.497875,6.532445],"angle":22.5,"axis":"z"}},{"from":[7.1433897,0.55847454,-6.1573944],"to":[7.1433897,4.5584745,0.8426051],"faces":{"east":{"uv":[4.75,3.125,3.0,4.125],"tintindex":0,"rotation":0,"texture":"#1"},"west":{"uv":[3.0,3.125,4.75,4.125],"tintindex":0,"rotation":0,"texture":"#1"}},"rotation":{"origin":[7.1433897,0.80847454,1.0926051],"angle":-22.5,"axis":"x"}},{"from":[7.8933897,-4.76365,4.847045],"to":[7.8933897,-2.26365,5.847045],"faces":{"east":{"uv":[8.125,0.625,7.875,0.0],"tintindex":0,"rotation":0,"texture":"#1"},"west":{"uv":[7.875,0.625,8.125,0.0],"tintindex":0,"rotation":0,"texture":"#1"}},"rotation":{"origin":[7.8933897,-1.6761503,12.209545],"angle":22.5,"axis":"x"}},{"from":[6.3933897,-2.383255,6.39067],"to":[7.8933897,-2.383255,7.39067],"faces":{"up":{"uv":[8.25,2.375,8.625,2.125],"tintindex":0,"rotation":0,"texture":"#1"},"down":{"uv":[8.25,2.125,8.625,2.375],"tintindex":0,"rotation":0,"texture":"#1"}},"rotation":{"origin":[7.1433897,-2.383255,3.6406698],"angle":-22.5,"axis":"x"}},{"from":[6.3933897,-2.383255,3.1406703],"to":[7.8933897,-2.383255,4.14067],"faces":{"up":{"uv":[8.25,2.375,8.625,2.125],"tintindex":0,"rotation":0,"texture":"#1"},"down":{"uv":[8.25,2.125,8.625,2.375],"tintindex":0,"rotation":0,"texture":"#1"}},"rotation":{"origin":[7.1433897,-2.383255,3.6406698],"angle":-22.5,"axis":"x"}},{"from":[6.3933897,-0.47075558,7.39067],"to":[7.8933897,-0.47075558,8.39067],"faces":{"up":{"uv":[8.625,2.375,8.25,2.125],"tintindex":0,"rotation":0,"texture":"#1"},"down":{"uv":[8.625,2.125,8.25,2.375],"tintindex":0,"rotation":0,"texture":"#1"}},"rotation":{"origin":[7.1433897,-2.383255,3.6406698],"angle":-22.5,"axis":"x"}},{"from":[6.6433897,-1.4415255,-0.6573944],"to":[7.6433897,3.0584745,0.8426051],"faces":{"east":{"uv":[3.375,5.75,3.0,6.875],"tintindex":0,"rotation":0,"texture":"#1"},"south":{"uv":[6.5,0.0,6.75,1.125],"tintindex":0,"rotation":0,"texture":"#1"},"north":{"uv":[6.25,6.375,6.5,7.5],"tintindex":0,"rotation":0,"texture":"#1"},"west":{"uv":[3.0,5.75,3.375,6.875],"tintindex":0,"rotation":0,"texture":"#1"},"up":{"uv":[6.75,8.375,6.5,8.0],"tintindex":0,"rotation":0,"texture":"#1"},"down":{"uv":[8.25,6.625,8.0,7.0],"tintindex":0,"rotation":0,"texture":"#1"}},"rotation":{"origin":[7.1433897,0.80847454,1.0926051],"angle":-22.5,"axis":"x"}},{"from":[4.1795197,10.26899,5.634615],"to":[5.6795197,10.26899,8.134615],"faces":{"up":{"uv":[6.75,4.0,7.125,4.625],"tintindex":0,"rotation":0,"texture":"#1"},"down":{"uv":[7.125,4.0,6.75,4.625],"tintindex":0,"rotation":180,"texture":"#1"}},"rotation":{"origin":[5.820095,9.01899,5.974875],"angle":45.0,"axis":"y"}},{"from":[6.3933897,-1.4136505,2.4335651],"to":[6.3933897,0.58634996,3.4335651],"faces":{"east":{"uv":[8.125,0.0,7.875,0.5],"tintindex":0,"rotation":0,"texture":"#1"},"west":{"uv":[7.875,0.0,8.125,0.5],"tintindex":0,"rotation":0,"texture":"#1"}},"rotation":{"origin":[6.3933897,-1.0386505,4.433565],"angle":-45.0,"axis":"x"}},{"from":[5.4719954,2.498005,9.860664],"to":[8.471994,3.498005,9.860664],"faces":{"south":{"uv":[11.5,12.0,12.25,12.25],"tintindex":0,"rotation":0,"texture":"#0"},"north":{"uv":[12.25,12.0,11.5,12.25],"tintindex":0,"rotation":0,"texture":"#0"}},"rotation":{"origin":[7.7800503,2.7108598,8.985664],"angle":-22.5,"axis":"z"}},{"from":[5.4719954,-1.5019951,9.860664],"to":[8.471994,-0.5019951,9.860664],"faces":{"south":{"uv":[11.5,12.0,12.25,12.25],"tintindex":0,"rotation":0,"texture":"#0"},"north":{"uv":[12.25,12.0,11.5,12.25],"tintindex":0,"rotation":0,"texture":"#0"}},"rotation":{"origin":[7.7800503,-1.2891407,8.985664],"angle":-22.5,"axis":"z"}},{"from":[6.6433897,-1.3521252,7.282445],"to":[7.6433897,0.14787483,13.782445],"faces":{"east":{"uv":[5.0,4.0,6.625,4.375],"tintindex":0,"rotation":0,"texture":"#1"},"south":{"uv":[8.0,5.25,8.25,5.625],"tintindex":0,"rotation":0,"texture":"#1"},"north":{"uv":[6.5,2.5,6.75,2.875],"tintindex":0,"rotation":0,"texture":"#1"},"west":{"uv":[5.0,4.5,6.625,4.875],"tintindex":0,"rotation":0,"texture":"#1"},"up":{"uv":[3.75,7.375,3.5,5.75],"tintindex":0,"rotation":0,"texture":"#1"},"down":{"uv":[4.125,5.75,3.875,7.375],"tintindex":0,"rotation":0,"texture":"#1"}},"rotation":{"origin":[7.1433897,-0.60212517,9.782445],"angle":22.5,"axis":"x"}},{"from":[5.8700695,3.8488493,6.532445],"to":[5.8700695,4.8488493,10.032445],"faces":{"east":{"uv":[12.75,0.75,11.875,1.0],"tintindex":0,"rotation":0,"texture":"#0"},"west":{"uv":[11.875,0.75,12.75,1.0],"tintindex":0,"rotation":0,"texture":"#0"}},"rotation":{"origin":[5.8700695,4.3488493,8.282445],"angle":22.5,"axis":"x"}},{"from":[6.6433897,-1.9477949,0.33841515],"to":[7.6433897,-0.4477949,8.338415],"faces":{"east":{"uv":[4.875,3.0,6.875,3.375],"tintindex":0,"rotation":0,"texture":"#1"},"south":{"uv":[8.375,4.125,8.625,4.5],"tintindex":0,"rotation":0,"texture":"#1"},"north":{"uv":[8.375,3.625,8.625,4.0],"tintindex":0,"rotation":0,"texture":"#1"},"west":{"uv":[4.875,3.5,6.875,3.875],"tintindex":0,"rotation":0,"texture":"#1"},"up":{"uv":[5.25,7.0,5.0,5.0],"tintindex":0,"rotation":0,"texture":"#1"},"down":{"uv":[5.625,5.0,5.375,7.0],"tintindex":0,"rotation":0,"texture":"#1"}},"rotation":{"origin":[7.1433897,-1.1977949,4.088415],"angle":-22.5,"axis":"x"}},{"from":[6.3933897,-2.383255,4.76567],"to":[7.8933897,-2.383255,5.76567],"faces":{"up":{"uv":[8.25,2.375,8.625,2.125],"tintindex":0,"rotation":0,"texture":"#1"},"down":{"uv":[8.25,2.125,8.625,2.375],"tintindex":0,"rotation":0,"texture":"#1"}},"rotation":{"origin":[7.1433897,-2.383255,3.6406698],"angle":-22.5,"axis":"x"}},{"from":[6.3933897,-0.47075558,4.14067],"to":[7.8933897,-0.47075558,5.14067],"faces":{"up":{"uv":[8.625,2.375,8.25,2.125],"tintindex":0,"rotation":0,"texture":"#1"},"down":{"uv":[8.625,2.125,8.25,2.375],"tintindex":0,"rotation":0,"texture":"#1"}},"rotation":{"origin":[7.1433897,-2.383255,3.6406698],"angle":-22.5,"axis":"x"}},{"from":[7.8933897,-5.9261503,3.7095451],"to":[7.8933897,-3.4261503,4.709545],"faces":{"east":{"uv":[8.125,0.625,7.875,0.0],"tintindex":0,"rotation":0,"texture":"#1"},"west":{"uv":[7.875,0.625,8.125,0.0],"tintindex":0,"rotation":0,"texture":"#1"}},"rotation":{"origin":[7.8933897,-1.6761503,12.209545],"angle":22.5,"axis":"x"}},{"from":[6.1433897,3.9978752,6.782445],"to":[8.14339,8.497875,8.782445],"faces":{"east":{"uv":[9.5,4.25,10.0,5.375],"tintindex":0,"rotation":0,"texture":"#0"},"south":{"uv":[1.625,9.5,2.125,10.625],"tintindex":0,"rotation":0,"texture":"#0"},"north":{"uv":[1.625,9.5,2.125,10.625],"tintindex":0,"rotation":0,"texture":"#0"},"west":{"uv":[9.5,4.25,10.0,5.375],"tintindex":0,"rotation":0,"texture":"#0"},"up":{"uv":[11.875,9.75,11.375,9.25],"tintindex":0,"rotation":0,"texture":"#0"},"down":{"uv":[11.875,9.875,11.375,10.375],"tintindex":0,"rotation":0,"texture":"#0"}}},{"from":[7.1433897,-2.447795,12.513415],"to":[7.1433897,1.0522046,20.513416],"faces":{"east":{"uv":[5.0,1.0,3.0,1.875],"tintindex":0,"rotation":0,"texture":"#1"},"west":{"uv":[3.0,1.0,5.0,1.875],"tintindex":0,"rotation":0,"texture":"#1"}},"rotation":{"origin":[7.1433897,-0.6977949,14.513415],"angle":-22.5,"axis":"x"}},{"from":[6.3933897,-2.6636505,5.433565],"to":[6.3933897,-0.6636505,6.433565],"faces":{"east":{"uv":[8.125,0.0,7.875,0.5],"tintindex":0,"rotation":0,"texture":"#1"},"west":{"uv":[7.875,0.0,8.125,0.5],"tintindex":0,"rotation":0,"texture":"#1"}},"rotation":{"origin":[6.3933897,-1.0386505,4.433565],"angle":-45.0,"axis":"x"}},{"from":[8.41671,2.4274297,6.207415],"to":[8.41671,3.4274297,9.207415],"faces":{"east":{"uv":[11.875,0.75,12.75,1.0],"tintindex":0,"rotation":0,"texture":"#0"},"west":{"uv":[12.75,0.75,11.875,1.0],"tintindex":0,"rotation":0,"texture":"#0"}},"rotation":{"origin":[7.7800503,3.1233597,8.985664],"angle":-22.5,"axis":"x"}},{"from":[6.3933897,-0.47075558,5.76567],"to":[7.8933897,-0.47075558,6.76567],"faces":{"up":{"uv":[8.625,2.375,8.25,2.125],"tintindex":0,"rotation":0,"texture":"#1"},"down":{"uv":[8.625,2.125,8.25,2.375],"tintindex":0,"rotation":0,"texture":"#1"}},"rotation":{"origin":[7.1433897,-2.383255,3.6406698],"angle":-22.5,"axis":"x"}},{"from":[8.41671,-0.0725708,6.207415],"to":[8.41671,0.9274297,9.207415],"faces":{"east":{"uv":[11.875,0.75,12.75,1.0],"tintindex":0,"rotation":0,"texture":"#0"},"west":{"uv":[12.75,0.75,11.875,1.0],"tintindex":0,"rotation":0,"texture":"#0"}},"rotation":{"origin":[7.7800503,0.6233597,8.985664],"angle":-22.5,"axis":"x"}},{"from":[5.6433897,2.9978747,6.532445],"to":[8.64339,3.9978752,6.532445],"faces":{"south":{"uv":[12.25,12.0,11.5,12.25],"tintindex":0,"rotation":0,"texture":"#0"},"north":{"uv":[11.5,12.0,12.25,12.25],"tintindex":0,"rotation":0,"texture":"#0"}},"rotation":{"origin":[7.1433897,3.4978747,6.532445],"angle":22.5,"axis":"z"}},{"from":[4.1795197,7.2689896,4.634615],"to":[5.6795197,8.26899,8.134615],"faces":{"east":{"uv":[6.875,7.875,6.625,7.0],"tintindex":0,"rotation":270,"texture":"#1"},"south":{"uv":[8.375,7.125,8.0,7.375],"tintindex":0,"rotation":0,"texture":"#1"},"north":{"uv":[7.25,8.25,6.875,8.0],"tintindex":0,"rotation":180,"texture":"#1"},"west":{"uv":[7.25,7.875,7.0,7.0],"tintindex":0,"rotation":90,"texture":"#1"},"up":{"uv":[6.0,0.0,6.375,0.875],"tintindex":0,"rotation":0,"texture":"#1"},"down":{"uv":[5.75,5.875,6.125,6.75],"tintindex":0,"rotation":180,"texture":"#1"}},"rotation":{"origin":[5.820095,9.01899,5.974875],"angle":45.0,"axis":"y"}},{"from":[6.3933897,-2.0386505,3.9335651],"to":[6.3933897,-0.038650513,4.933565],"faces":{"east":{"uv":[8.125,0.0,7.875,0.5],"tintindex":0,"rotation":0,"texture":"#1"},"west":{"uv":[7.875,0.0,8.125,0.5],"tintindex":0,"rotation":0,"texture":"#1"}},"rotation":{"origin":[6.3933897,-1.0386505,4.433565],"angle":-45.0,"axis":"x"}},{"from":[5.4719954,0.4980049,9.860664],"to":[8.471994,1.4980049,9.860664],"faces":{"south":{"uv":[11.5,12.0,12.25,12.25],"tintindex":0,"rotation":0,"texture":"#0"},"north":{"uv":[12.25,12.0,11.5,12.25],"tintindex":0,"rotation":0,"texture":"#0"}},"rotation":{"origin":[7.7800503,0.7108598,8.985664],"angle":-22.5,"axis":"z"}},{"from":[4.1795197,8.26899,4.634615],"to":[5.6795197,10.26899,5.634615],"faces":{"east":{"uv":[6.875,5.75,6.375,5.5],"tintindex":0,"rotation":270,"texture":"#1"},"south":{"uv":[5.125,7.125,4.75,7.625],"tintindex":0,"rotation":0,"texture":"#1"},"north":{"uv":[4.625,7.625,4.25,7.125],"tintindex":0,"rotation":180,"texture":"#1"},"west":{"uv":[3.125,8.0,2.625,7.75],"tintindex":0,"rotation":90,"texture":"#1"},"up":{"uv":[0.5,8.125,0.875,8.375],"tintindex":0,"rotation":0,"texture":"#1"},"down":{"uv":[0.0,8.125,0.375,8.375],"tintindex":0,"rotation":180,"texture":"#1"}},"rotation":{"origin":[5.820095,9.01899,5.974875],"angle":45.0,"axis":"y"}},{"from":[6.0692654,10.26899,5.51084],"to":[7.569265,10.26899,8.010839],"faces":{"up":{"uv":[7.375,2.5,7.0,3.125],"tintindex":0,"rotation":0,"texture":"#1"},"down":{"uv":[2.875,7.0,2.5,7.625],"tintindex":0,"rotation":180,"texture":"#1"}},"rotation":{"origin":[5.820095,9.01899,5.974875],"angle":22.5,"axis":"y"}},{"from":[7.8933897,-3.63865,5.972045],"to":[7.8933897,-1.13865,6.972045],"faces":{"east":{"uv":[8.125,0.625,7.875,0.0],"tintindex":0,"rotation":0,"texture":"#1"},"west":{"uv":[7.875,0.625,8.125,0.0],"tintindex":0,"rotation":0,"texture":"#1"}},"rotation":{"origin":[7.8933897,-1.6761503,12.209545],"angle":22.5,"axis":"x"}},{"from":[7.1433897,-5.447795,2.3384151],"to":[7.1433897,1.5522046,7.338415],"faces":{"east":{"uv":[2.625,0.0,1.375,1.75],"tintindex":0,"rotation":0,"texture":"#1"},"west":{"uv":[1.375,0.0,2.625,1.75],"tintindex":0,"rotation":0,"texture":"#1"}},"rotation":{"origin":[7.1433897,-1.1977949,4.088415],"angle":-22.5,"axis":"x"}},{"from":[7.1433897,-0.44152546,0.8426051],"to":[7.1433897,3.0584745,4.8426046],"faces":{"east":{"uv":[5.875,2.0,4.875,2.875],"tintindex":0,"rotation":0,"texture":"#1"},"west":{"uv":[4.875,2.0,5.875,2.875],"tintindex":0,"rotation":0,"texture":"#1"}},"rotation":{"origin":[7.1433897,0.80847454,1.0926051],"angle":-22.5,"axis":"x"}},{"from":[5.4719954,4.998005,9.235664],"to":[8.471994,5.998005,9.235664],"faces":{"south":{"uv":[11.5,12.0,12.25,12.25],"tintindex":0,"rotation":0,"texture":"#0"},"north":{"uv":[12.25,12.0,11.5,12.25],"tintindex":0,"rotation":0,"texture":"#0"}},"rotation":{"origin":[7.7800503,5.2108593,8.360664],"angle":-22.5,"axis":"z"}},{"from":[6.0692654,7.2689896,4.51084],"to":[7.569265,8.26899,8.010839],"faces":{"east":{"uv":[7.125,1.625,7.375,0.75],"tintindex":0,"rotation":270,"texture":"#1"},"south":{"uv":[4.75,8.125,5.125,8.375],"tintindex":0,"rotation":0,"texture":"#1"},"north":{"uv":[4.25,8.375,4.625,8.125],"tintindex":0,"rotation":180,"texture":"#1"},"west":{"uv":[0.75,8.0,1.0,7.125],"tintindex":0,"rotation":90,"texture":"#1"},"up":{"uv":[1.375,6.125,1.0,7.0],"tintindex":0,"rotation":0,"texture":"#1"},"down":{"uv":[0.875,6.125,0.5,7.0],"tintindex":0,"rotation":180,"texture":"#1"}},"rotation":{"origin":[5.820095,9.01899,5.974875],"angle":22.5,"axis":"y"}}],"display":{"gui":{"rotation":[-150.0,-45.0,180.0]}},"gui_light":"front"}