{"textures":{"0":"modelengine:entity/mob_ent_brute","particle":"#0"},"elements":[{"from":[2.25,9.37929,13.219465],"to":[13.75,9.37929,20.219465],"faces":{"up":{"uv":[1.4375,3.125,0.0,2.25],"tintindex":0,"rotation":0,"texture":"#0"},"down":{"uv":[1.4375,2.25,0.0,3.125],"tintindex":0,"rotation":0,"texture":"#0"}},"rotation":{"origin":[8.75,6.6904297,5.2235],"angle":-22.5,"axis":"x"}},{"from":[2.25,9.37929,13.219465],"to":[2.25,17.87929,20.219465],"faces":{"east":{"uv":[2.75,3.6875,1.875,4.75],"tintindex":0,"rotation":0,"texture":"#0"},"west":{"uv":[1.875,3.6875,2.75,4.75],"tintindex":0,"rotation":0,"texture":"#0"}},"rotation":{"origin":[7.25,6.6904297,5.2235],"angle":-22.5,"axis":"x"}},{"from":[4.75,4.722315,5.979365],"to":[4.75,7.722315,9.979364],"faces":{"east":{"uv":[8.25,4.25,8.75,4.625],"tintindex":0,"rotation":0,"texture":"#0"},"west":{"uv":[8.75,4.25,8.25,4.625],"tintindex":0,"rotation":0,"texture":"#0"}}},{"from":[13.75,9.37929,13.219465],"to":[13.75,17.87929,20.219465],"faces":{"east":{"uv":[2.75,3.6875,1.875,4.75],"tintindex":0,"rotation":0,"texture":"#0"},"west":{"uv":[1.875,3.6875,2.75,4.75],"tintindex":0,"rotation":0,"texture":"#0"}},"rotation":{"origin":[8.75,6.6904297,5.2235],"angle":-22.5,"axis":"x"}},{"from":[2.25,9.37929,6.2194653],"to":[13.75,13.87929,13.219465],"faces":{"east":{"uv":[6.875,4.625,6.0,5.1875],"tintindex":0,"rotation":0,"texture":"#0"},"south":{"uv":[4.625,3.375,6.0625,3.9375],"tintindex":0,"rotation":0,"texture":"#0"},"north":{"uv":[4.5,0.0,5.9375,0.5625],"tintindex":0,"rotation":0,"texture":"#0"},"west":{"uv":[6.0,4.625,6.875,5.1875],"tintindex":0,"rotation":0,"texture":"#0"},"up":{"uv":[2.9375,0.875,1.5,0.0],"tintindex":0,"rotation":0,"texture":"#0"},"down":{"uv":[2.9375,0.9375,1.5,1.8125],"tintindex":0,"rotation":0,"texture":"#0"}},"rotation":{"origin":[8.75,6.6904297,5.2235],"angle":-22.5,"axis":"x"}},{"from":[4.75,4.722315,5.979365],"to":[11.25,7.722315,5.979365],"faces":{"south":{"uv":[8.125,5.4375,7.3125,5.8125],"tintindex":0,"rotation":0,"texture":"#0"},"north":{"uv":[7.3125,5.4375,8.125,5.8125],"tintindex":0,"rotation":0,"texture":"#0"}}},{"from":[11.25,4.722315,5.979365],"to":[11.25,7.722315,9.979364],"faces":{"east":{"uv":[8.25,4.25,8.75,4.625],"tintindex":0,"rotation":0,"texture":"#0"},"west":{"uv":[8.75,4.25,8.25,4.625],"tintindex":0,"rotation":0,"texture":"#0"}}},{"from":[4.75,7.722315,5.979365],"to":[11.25,11.722315,9.979364],"faces":{"east":{"uv":[5.75,7.6875,6.25,8.1875],"tintindex":0,"rotation":0,"texture":"#0"},"south":{"uv":[6.0,5.25,6.8125,5.75],"tintindex":0,"rotation":0,"texture":"#0"},"north":{"uv":[5.0,6.0,5.8125,6.5],"tintindex":0,"rotation":0,"texture":"#0"},"west":{"uv":[6.25,7.6875,5.75,8.1875],"tintindex":0,"rotation":0,"texture":"#0"},"up":{"uv":[6.8125,6.3125,6.0,5.8125],"tintindex":0,"rotation":0,"texture":"#0"},"down":{"uv":[6.9375,3.375,6.125,3.875],"tintindex":0,"rotation":0,"texture":"#0"}}},{"from":[2.25,9.37929,20.219465],"to":[13.75,17.87929,20.219465],"faces":{"south":{"uv":[0.0,1.125,1.4375,2.1875],"tintindex":0,"rotation":0,"texture":"#0"},"north":{"uv":[1.4375,1.125,0.0,2.1875],"tintindex":0,"rotation":0,"texture":"#0"}},"rotation":{"origin":[8.75,6.6904297,5.2235],"angle":-22.5,"axis":"x"}},{"from":[4.75,4.722315,9.979364],"to":[11.25,7.722315,9.979364],"faces":{"south":{"uv":[7.4375,2.9375,8.25,3.3125],"tintindex":0,"rotation":0,"texture":"#0"},"north":{"uv":[8.25,2.9375,7.4375,3.3125],"tintindex":0,"rotation":0,"texture":"#0"}}}],"display":{"gui":{"rotation":[-150.0,-45.0,180.0]}},"gui_light":"front"}